{
  "feedback": [
    {
      "id": 1,
      "rating": 10,
      "user_name": "Tony Stark",
      "text": "You are the ironman of this world"
    },
    {
      "id": 2,
      "rating": 9,
      "user_name": "Bruce Wayne",
      "text": "You are the batman of this world"
    },
    {
      "id": 3,
      "rating": 8,
      "user_name": "Peter Parker",
      "text": "You are the spiderman of this world"
    },
    {
      "id": 4,
      "rating": 90,
      "user_name": "Bruce Wayne",
      "text": "You are the batman of this world"
    },
    {
      "id": 5,
      "rating": 990,
      "user_name": "Bruce Wayne",
      "text": "You are the batman of this world"
    }
  ],
  "todos":[
    {
      "id":1,
      "task":"Playing",
      "status":"pending"
    }
  ],
  "users": [
    {
      "id": 1,
      "username": "soumya",
      "email": "soumya@gmail.com",
      "password": "soumya"
    }
  ]
}